ethopy/.DS_Store
ethopy/__init__.py
ethopy/__main__.py
ethopy/common.py
ethopy/ethopy.py
ethopy/Behaviors/MultiPort.py
ethopy/Behaviors/__init__.py
ethopy/Experiments/MatchPort.py
ethopy/Experiments/__init__.py
ethopy/Interfaces/DummyPorts.py
ethopy/Interfaces/__init__.py
ethopy/Stimuli/Grating.py
ethopy/Stimuli/__init__.py
ethopy/conf/grating_test.py
ethopy/core/Behavior.py
ethopy/core/Experiment.py
ethopy/core/Interface.py
ethopy/core/Logger.py
ethopy/core/Stimulus.py
ethopy/core/__init__.py
ethopy/utils/Presenter.py
ethopy/utils/Start.py
ethopy/utils/ThreadWorker.py
ethopy/utils/Timer.py
ethopy/utils/TouchInterface.py
ethopy/utils/Writer.py
ethopy/utils/__init__.py
ethopy/utils/helper_functions.py
ethopy/utils/plantuml/behavior.iuml
ethopy/utils/plantuml/experiments.iuml
ethopy/utils/plantuml/modules.iuml
ethopy/utils/plantuml/state_functions.iuml
ethopy/utils/plantuml/states.iuml
ethopy/utils/plantuml/stimuli.iuml
testcore-0.0.3.dist-info/LICENSE
testcore-0.0.3.dist-info/METADATA
testcore-0.0.3.dist-info/WHEEL
testcore-0.0.3.dist-info/entry_points.txt
testcore-0.0.3.dist-info/top_level.txt
testcore-0.0.3.dist-info/RECORD
